<?xml version="1.0" encoding="UTF-8"?>
<measurements>
	<measurement>
		<date>1449950595</date>
		<errorCode>0</errorCode>
		<numberOfThreads>11</numberOfThreads>
		<processors>12</processors>
		<hostname>e1341</hostname>
		<totalTime>0.889544</totalTime>
		<algorithm>locallist</algorithm>
		<threads>
			<thread>
			<id>0</id>
			<timings>
				<timing name="barrier">0.0002726</timing>
				<timing name="criticalPushBack">1.6413e-05</timing>
				<timing name="criticalRequestValueUpdate">0.0642146</timing>
				<timing name="currentGather">1.334e-05</timing>
				<timing name="currentScatter">0.063743</timing>
			</timings>
			<processedNodes>90923</processedNodes>
			</thread>
			<thread>
			<id>1</id>
			<timings>
				<timing name="barrier">0.000235585</timing>
				<timing name="criticalPushBack">2.5395e-05</timing>
				<timing name="criticalRequestValueUpdate">0.0627445</timing>
				<timing name="currentGather">3.0112e-05</timing>
				<timing name="currentScatter">0.0633996</timing>
			</timings>
			<processedNodes>90928</processedNodes>
			</thread>
			<thread>
			<id>2</id>
			<timings>
				<timing name="barrier">0.000264984</timing>
				<timing name="criticalPushBack">1.7729e-05</timing>
				<timing name="criticalRequestValueUpdate">0.0628623</timing>
				<timing name="currentGather">1.9986e-05</timing>
				<timing name="currentScatter">0.0610041</timing>
			</timings>
			<processedNodes>90938</processedNodes>
			</thread>
			<thread>
			<id>3</id>
			<timings>
				<timing name="barrier">0.000229479</timing>
				<timing name="criticalPushBack">2.4341e-05</timing>
				<timing name="criticalRequestValueUpdate">0.0677093</timing>
				<timing name="currentGather">2.5128e-05</timing>
				<timing name="currentScatter">0.0497558</timing>
			</timings>
			<processedNodes>90930</processedNodes>
			</thread>
			<thread>
			<id>4</id>
			<timings>
				<timing name="barrier">6.4596e-05</timing>
				<timing name="criticalPushBack">9.277e-06</timing>
				<timing name="criticalRequestValueUpdate">0.0574244</timing>
				<timing name="currentGather">1.1297e-05</timing>
				<timing name="currentScatter">0.0600903</timing>
			</timings>
			<processedNodes>90928</processedNodes>
			</thread>
			<thread>
			<id>5</id>
			<timings>
				<timing name="barrier">6.7876e-05</timing>
				<timing name="criticalPushBack">8.18e-06</timing>
				<timing name="criticalRequestValueUpdate">0.0576594</timing>
				<timing name="currentGather">9.977e-06</timing>
				<timing name="currentScatter">0.0689952</timing>
			</timings>
			<processedNodes>90929</processedNodes>
			</thread>
			<thread>
			<id>6</id>
			<timings>
				<timing name="barrier">4.3054e-05</timing>
				<timing name="criticalPushBack">9.668e-06</timing>
				<timing name="criticalRequestValueUpdate">0.056456</timing>
				<timing name="currentGather">8.909e-06</timing>
				<timing name="currentScatter">0.0645514</timing>
			</timings>
			<processedNodes>90935</processedNodes>
			</thread>
			<thread>
			<id>7</id>
			<timings>
				<timing name="barrier">4.2323e-05</timing>
				<timing name="criticalPushBack">1.5326e-05</timing>
				<timing name="criticalRequestValueUpdate">0.0554919</timing>
				<timing name="currentGather">1.587e-05</timing>
				<timing name="currentScatter">0.0569721</timing>
			</timings>
			<processedNodes>90913</processedNodes>
			</thread>
			<thread>
			<id>8</id>
			<timings>
				<timing name="barrier">7.4059e-05</timing>
				<timing name="criticalPushBack">1.0061e-05</timing>
				<timing name="criticalRequestValueUpdate">0.0564086</timing>
				<timing name="currentGather">1.1646e-05</timing>
				<timing name="currentScatter">0.0512616</timing>
			</timings>
			<processedNodes>90926</processedNodes>
			</thread>
			<thread>
			<id>9</id>
			<timings>
				<timing name="barrier">0.00011829</timing>
				<timing name="criticalPushBack">1.2356e-05</timing>
				<timing name="criticalRequestValueUpdate">0.0569591</timing>
				<timing name="currentGather">1.0968e-05</timing>
				<timing name="currentScatter">0.0509226</timing>
			</timings>
			<processedNodes>90935</processedNodes>
			</thread>
			<thread>
			<id>10</id>
			<timings>
				<timing name="barrier">0.000124186</timing>
				<timing name="criticalPushBack">1.3399e-05</timing>
				<timing name="criticalRequestValueUpdate">0.0559166</timing>
				<timing name="currentGather">1.1537e-05</timing>
				<timing name="currentScatter">0.056921</timing>
			</timings>
			<processedNodes>90918</processedNodes>
			</thread>
		</threads>
		<graph>
			<type>RANDOMLIN</type>
			<numberOfNodes>1000000</numberOfNodes>
			<numberOfEdges>2699997</numberOfEdges>
			<depth>21</depth>
		</graph>
		<optimistic>false</optimistic>
		<enableAnalysis>true</enableAnalysis>
	</measurement>
</measurements>
