<?xml version="1.0" encoding="UTF-8"?>
<measurements>
	<measurement>
		<date>1449637068</date>
		<errorCode>0</errorCode>
		<numberOfThreads>23</numberOfThreads>
		<processors>24</processors>
		<hostname>e1070</hostname>
		<totalTime>26.7163</totalTime>
		<algorithm>locallist</algorithm>
		<threads>
			<thread>
			<id>0</id>
			<timings>
				<timing name="barrier">0.00063036</timing>
				<timing name="criticalPushBack">0.000111089</timing>
				<timing name="criticalRequestValueUpdate">0.803509</timing>
				<timing name="currentGather">0.000196161</timing>
				<timing name="currentScatter">3.51179</timing>
			</timings>
			<processedNodes>434823</processedNodes>
			</thread>
			<thread>
			<id>1</id>
			<timings>
				<timing name="barrier">0.000498129</timing>
				<timing name="criticalPushBack">0.000196711</timing>
				<timing name="criticalRequestValueUpdate">0.858455</timing>
				<timing name="currentGather">0.000128287</timing>
				<timing name="currentScatter">3.47738</timing>
			</timings>
			<processedNodes>434829</processedNodes>
			</thread>
			<thread>
			<id>2</id>
			<timings>
				<timing name="barrier">0.000528132</timing>
				<timing name="criticalPushBack">0.000253591</timing>
				<timing name="criticalRequestValueUpdate">0.824893</timing>
				<timing name="currentGather">0.000158082</timing>
				<timing name="currentScatter">2.06597</timing>
			</timings>
			<processedNodes>434837</processedNodes>
			</thread>
			<thread>
			<id>3</id>
			<timings>
				<timing name="barrier">0.000718866</timing>
				<timing name="criticalPushBack">9.3861e-05</timing>
				<timing name="criticalRequestValueUpdate">0.763642</timing>
				<timing name="currentGather">9.4193e-05</timing>
				<timing name="currentScatter">2.8569</timing>
			</timings>
			<processedNodes>434804</processedNodes>
			</thread>
			<thread>
			<id>4</id>
			<timings>
				<timing name="barrier">0.000476516</timing>
				<timing name="criticalPushBack">0.000110467</timing>
				<timing name="criticalRequestValueUpdate">0.762882</timing>
				<timing name="currentGather">0.00013748</timing>
				<timing name="currentScatter">3.6332</timing>
			</timings>
			<processedNodes>434830</processedNodes>
			</thread>
			<thread>
			<id>5</id>
			<timings>
				<timing name="barrier">0.00049014</timing>
				<timing name="criticalPushBack">9.5001e-05</timing>
				<timing name="criticalRequestValueUpdate">0.740409</timing>
				<timing name="currentGather">9.9229e-05</timing>
				<timing name="currentScatter">3.60644</timing>
			</timings>
			<processedNodes>434831</processedNodes>
			</thread>
			<thread>
			<id>6</id>
			<timings>
				<timing name="barrier">0.000641141</timing>
				<timing name="criticalPushBack">0.000121799</timing>
				<timing name="criticalRequestValueUpdate">0.77542</timing>
				<timing name="currentGather">8.8609e-05</timing>
				<timing name="currentScatter">3.76175</timing>
			</timings>
			<processedNodes>434827</processedNodes>
			</thread>
			<thread>
			<id>7</id>
			<timings>
				<timing name="barrier">0.000591595</timing>
				<timing name="criticalPushBack">0.000125118</timing>
				<timing name="criticalRequestValueUpdate">0.749863</timing>
				<timing name="currentGather">0.000214587</timing>
				<timing name="currentScatter">3.88107</timing>
			</timings>
			<processedNodes>434832</processedNodes>
			</thread>
			<thread>
			<id>8</id>
			<timings>
				<timing name="barrier">0.00074691</timing>
				<timing name="criticalPushBack">0.00021813</timing>
				<timing name="criticalRequestValueUpdate">0.772627</timing>
				<timing name="currentGather">0.000324044</timing>
				<timing name="currentScatter">2.60217</timing>
			</timings>
			<processedNodes>434833</processedNodes>
			</thread>
			<thread>
			<id>9</id>
			<timings>
				<timing name="barrier">0.000618751</timing>
				<timing name="criticalPushBack">0.00022347</timing>
				<timing name="criticalRequestValueUpdate">0.765946</timing>
				<timing name="currentGather">0.000243768</timing>
				<timing name="currentScatter">2.70819</timing>
			</timings>
			<processedNodes>434841</processedNodes>
			</thread>
			<thread>
			<id>10</id>
			<timings>
				<timing name="barrier">0.000667253</timing>
				<timing name="criticalPushBack">0.000333324</timing>
				<timing name="criticalRequestValueUpdate">0.833793</timing>
				<timing name="currentGather">0.00032229</timing>
				<timing name="currentScatter">3.75662</timing>
			</timings>
			<processedNodes>434823</processedNodes>
			</thread>
			<thread>
			<id>11</id>
			<timings>
				<timing name="barrier">0.000627283</timing>
				<timing name="criticalPushBack">0.000275985</timing>
				<timing name="criticalRequestValueUpdate">0.771444</timing>
				<timing name="currentGather">0.00020079</timing>
				<timing name="currentScatter">3.30709</timing>
			</timings>
			<processedNodes>434808</processedNodes>
			</thread>
			<thread>
			<id>12</id>
			<timings>
				<timing name="barrier">0.000857455</timing>
				<timing name="criticalPushBack">0.000278018</timing>
				<timing name="criticalRequestValueUpdate">0.880665</timing>
				<timing name="currentGather">0.000180377</timing>
				<timing name="currentScatter">3.0425</timing>
			</timings>
			<processedNodes>434834</processedNodes>
			</thread>
			<thread>
			<id>13</id>
			<timings>
				<timing name="barrier">0.000974855</timing>
				<timing name="criticalPushBack">0.000241458</timing>
				<timing name="criticalRequestValueUpdate">0.917831</timing>
				<timing name="currentGather">0.00025946</timing>
				<timing name="currentScatter">3.89712</timing>
			</timings>
			<processedNodes>434802</processedNodes>
			</thread>
			<thread>
			<id>14</id>
			<timings>
				<timing name="barrier">0.000884487</timing>
				<timing name="criticalPushBack">0.000373596</timing>
				<timing name="criticalRequestValueUpdate">0.932982</timing>
				<timing name="currentGather">0.000284061</timing>
				<timing name="currentScatter">3.79429</timing>
			</timings>
			<processedNodes>434850</processedNodes>
			</thread>
			<thread>
			<id>15</id>
			<timings>
				<timing name="barrier">0.000840783</timing>
				<timing name="criticalPushBack">0.000287317</timing>
				<timing name="criticalRequestValueUpdate">0.898249</timing>
				<timing name="currentGather">0.000204526</timing>
				<timing name="currentScatter">3.56825</timing>
			</timings>
			<processedNodes>434829</processedNodes>
			</thread>
			<thread>
			<id>16</id>
			<timings>
				<timing name="barrier">0.000901396</timing>
				<timing name="criticalPushBack">0.000291263</timing>
				<timing name="criticalRequestValueUpdate">0.91617</timing>
				<timing name="currentGather">0.000333134</timing>
				<timing name="currentScatter">3.49861</timing>
			</timings>
			<processedNodes>434821</processedNodes>
			</thread>
			<thread>
			<id>17</id>
			<timings>
				<timing name="barrier">0.000933537</timing>
				<timing name="criticalPushBack">0.000245075</timing>
				<timing name="criticalRequestValueUpdate">0.861316</timing>
				<timing name="currentGather">0.000286795</timing>
				<timing name="currentScatter">3.76905</timing>
			</timings>
			<processedNodes>434811</processedNodes>
			</thread>
			<thread>
			<id>18</id>
			<timings>
				<timing name="barrier">0.00102871</timing>
				<timing name="criticalPushBack">0.000256053</timing>
				<timing name="criticalRequestValueUpdate">0.899104</timing>
				<timing name="currentGather">0.00038061</timing>
				<timing name="currentScatter">3.59994</timing>
			</timings>
			<processedNodes>434849</processedNodes>
			</thread>
			<thread>
			<id>19</id>
			<timings>
				<timing name="barrier">0.00105861</timing>
				<timing name="criticalPushBack">0.000327952</timing>
				<timing name="criticalRequestValueUpdate">0.748732</timing>
				<timing name="currentGather">0.000355507</timing>
				<timing name="currentScatter">3.60731</timing>
			</timings>
			<processedNodes>434801</processedNodes>
			</thread>
			<thread>
			<id>20</id>
			<timings>
				<timing name="barrier">0.000899583</timing>
				<timing name="criticalPushBack">0.000360612</timing>
				<timing name="criticalRequestValueUpdate">0.801848</timing>
				<timing name="currentGather">0.000349502</timing>
				<timing name="currentScatter">3.54823</timing>
			</timings>
			<processedNodes>434825</processedNodes>
			</thread>
			<thread>
			<id>21</id>
			<timings>
				<timing name="barrier">0.00114669</timing>
				<timing name="criticalPushBack">0.000473471</timing>
				<timing name="criticalRequestValueUpdate">0.849532</timing>
				<timing name="currentGather">0.000425443</timing>
				<timing name="currentScatter">2.94023</timing>
			</timings>
			<processedNodes>434847</processedNodes>
			</thread>
			<thread>
			<id>22</id>
			<timings>
				<timing name="barrier">0.0011564</timing>
				<timing name="criticalPushBack">0.000541227</timing>
				<timing name="criticalRequestValueUpdate">0.851907</timing>
				<timing name="currentGather">0.000305081</timing>
				<timing name="currentScatter">2.73186</timing>
			</timings>
			<processedNodes>434842</processedNodes>
			</thread>
		</threads>
		<graph>
			<type>SOFTWARE</type>
			<numberOfNodes>10000000</numberOfNodes>
			<numberOfEdges>26974371</numberOfEdges>
			<depth>47</depth>
		</graph>
		<optimistic>false</optimistic>
		<enableAnalysis>true</enableAnalysis>
	</measurement>
</measurements>
