<?xml version="1.0" encoding="UTF-8"?>
<measurements>
	<measurement>
		<date>1449621472</date>
		<errorCode>0</errorCode>
		<numberOfThreads>13</numberOfThreads>
		<processors>24</processors>
		<hostname>e1070</hostname>
		<totalTime>13.5944</totalTime>
		<algorithm>locallist</algorithm>
		<threads>
			<thread>
			<id>0</id>
			<timings>
				<timing name="barrier">0.000509896</timing>
				<timing name="criticalPushBack">2.5573e-05</timing>
				<timing name="criticalRequestValueUpdate">0.625559</timing>
				<timing name="currentGather">2.8465e-05</timing>
				<timing name="currentScatter">2.31412</timing>
			</timings>
			<processedNodes>769258</processedNodes>
			</thread>
			<thread>
			<id>1</id>
			<timings>
				<timing name="barrier">0.000284175</timing>
				<timing name="criticalPushBack">3.5346e-05</timing>
				<timing name="criticalRequestValueUpdate">0.609522</timing>
				<timing name="currentGather">2.578e-05</timing>
				<timing name="currentScatter">2.2795</timing>
			</timings>
			<processedNodes>769252</processedNodes>
			</thread>
			<thread>
			<id>2</id>
			<timings>
				<timing name="barrier">0.000217619</timing>
				<timing name="criticalPushBack">2.9782e-05</timing>
				<timing name="criticalRequestValueUpdate">0.626014</timing>
				<timing name="currentGather">3.1621e-05</timing>
				<timing name="currentScatter">2.46965</timing>
			</timings>
			<processedNodes>769258</processedNodes>
			</thread>
			<thread>
			<id>3</id>
			<timings>
				<timing name="barrier">0.000660588</timing>
				<timing name="criticalPushBack">2.597e-05</timing>
				<timing name="criticalRequestValueUpdate">0.622522</timing>
				<timing name="currentGather">3.2693e-05</timing>
				<timing name="currentScatter">2.4074</timing>
			</timings>
			<processedNodes>769253</processedNodes>
			</thread>
			<thread>
			<id>4</id>
			<timings>
				<timing name="barrier">0.000216359</timing>
				<timing name="criticalPushBack">1.024e-05</timing>
				<timing name="criticalRequestValueUpdate">0.575486</timing>
				<timing name="currentGather">1.1379e-05</timing>
				<timing name="currentScatter">2.4411</timing>
			</timings>
			<processedNodes>769246</processedNodes>
			</thread>
			<thread>
			<id>5</id>
			<timings>
				<timing name="barrier">0.000192562</timing>
				<timing name="criticalPushBack">9.963e-06</timing>
				<timing name="criticalRequestValueUpdate">0.575333</timing>
				<timing name="currentGather">1.2627e-05</timing>
				<timing name="currentScatter">2.56438</timing>
			</timings>
			<processedNodes>769254</processedNodes>
			</thread>
			<thread>
			<id>6</id>
			<timings>
				<timing name="barrier">0.000208123</timing>
				<timing name="criticalPushBack">1.0737e-05</timing>
				<timing name="criticalRequestValueUpdate">0.573756</timing>
				<timing name="currentGather">1.7357e-05</timing>
				<timing name="currentScatter">2.34903</timing>
			</timings>
			<processedNodes>769255</processedNodes>
			</thread>
			<thread>
			<id>7</id>
			<timings>
				<timing name="barrier">0.000218155</timing>
				<timing name="criticalPushBack">1.1927e-05</timing>
				<timing name="criticalRequestValueUpdate">0.578871</timing>
				<timing name="currentGather">1.3513e-05</timing>
				<timing name="currentScatter">2.72352</timing>
			</timings>
			<processedNodes>769255</processedNodes>
			</thread>
			<thread>
			<id>8</id>
			<timings>
				<timing name="barrier">0.000218513</timing>
				<timing name="criticalPushBack">1.4171e-05</timing>
				<timing name="criticalRequestValueUpdate">0.571011</timing>
				<timing name="currentGather">2.8139e-05</timing>
				<timing name="currentScatter">2.62647</timing>
			</timings>
			<processedNodes>769233</processedNodes>
			</thread>
			<thread>
			<id>9</id>
			<timings>
				<timing name="barrier">0.000259585</timing>
				<timing name="criticalPushBack">1.3524e-05</timing>
				<timing name="criticalRequestValueUpdate">0.576516</timing>
				<timing name="currentGather">1.6264e-05</timing>
				<timing name="currentScatter">2.93168</timing>
			</timings>
			<processedNodes>769245</processedNodes>
			</thread>
			<thread>
			<id>10</id>
			<timings>
				<timing name="barrier">0.000284151</timing>
				<timing name="criticalPushBack">1.3627e-05</timing>
				<timing name="criticalRequestValueUpdate">0.604447</timing>
				<timing name="currentGather">1.9739e-05</timing>
				<timing name="currentScatter">2.71295</timing>
			</timings>
			<processedNodes>769247</processedNodes>
			</thread>
			<thread>
			<id>11</id>
			<timings>
				<timing name="barrier">0.000208069</timing>
				<timing name="criticalPushBack">1.5625e-05</timing>
				<timing name="criticalRequestValueUpdate">0.6128</timing>
				<timing name="currentGather">2.3055e-05</timing>
				<timing name="currentScatter">2.23374</timing>
			</timings>
			<processedNodes>769249</processedNodes>
			</thread>
			<thread>
			<id>12</id>
			<timings>
				<timing name="barrier">0.000263764</timing>
				<timing name="criticalPushBack">3.1422e-05</timing>
				<timing name="criticalRequestValueUpdate">0.904825</timing>
				<timing name="currentGather">2.89e-05</timing>
				<timing name="currentScatter">1.03154</timing>
			</timings>
			<processedNodes>769258</processedNodes>
			</thread>
		</threads>
		<graph>
			<type>RANDOMLIN</type>
			<numberOfNodes>10000000</numberOfNodes>
			<numberOfEdges>26999987</numberOfEdges>
			<depth>23</depth>
		</graph>
		<optimistic>false</optimistic>
		<enableAnalysis>true</enableAnalysis>
	</measurement>
</measurements>
