<?xml version="1.0" encoding="UTF-8"?>
<measurements>
	<measurement>
		<date>1451570429</date>
		<errorCode>0</errorCode>
		<numberOfThreads>23</numberOfThreads>
		<processors>24</processors>
		<hostname>e1390</hostname>
		<totalTime>0.486239</totalTime>
		<algorithm>locallist</algorithm>
		<graph>
			<type>RANDOMLIN</type>
			<numberOfNodes>1000000</numberOfNodes>
			<numberOfEdges>29999064</numberOfEdges>
			<depth>159</depth>
		</graph>
		<optimistic>true</optimistic>
		<enableAnalysis>false</enableAnalysis>
	</measurement>
</measurements>
