<?xml version="1.0" encoding="UTF-8"?>
<measurements>
	<measurement>
		<date>1452718069</date>
		<errorCode>0</errorCode>
		<numberOfThreads>20</numberOfThreads>
		<processors>24</processors>
		<hostname>e1178</hostname>
		<totalTime>0.388788</totalTime>
		<algorithm>worksteal</algorithm>
		<graph>
			<type>SOFTWARE</type>
			<numberOfNodes>2000000</numberOfNodes>
			<numberOfEdges>5391692</numberOfEdges>
			<depth>43</depth>
		</graph>
		<optimistic>true</optimistic>
		<enableAnalysis>false</enableAnalysis>
	</measurement>
</measurements>
