<?xml version="1.0" encoding="UTF-8"?>
<measurements>
	<measurement>
		<date>1449637773</date>
		<errorCode>0</errorCode>
		<numberOfThreads>9</numberOfThreads>
		<processors>24</processors>
		<hostname>e1070</hostname>
		<totalTime>6.22654</totalTime>
		<algorithm>locallist</algorithm>
		<threads>
			<thread>
			<id>0</id>
			<timings>
				<timing name="barrier">0.000883807</timing>
				<timing name="criticalPushBack">2.6976e-05</timing>
				<timing name="criticalRequestValueUpdate">0.497994</timing>
				<timing name="currentGather">3.7735e-05</timing>
				<timing name="currentScatter">1.20923</timing>
			</timings>
			<processedNodes>1111168</processedNodes>
			</thread>
			<thread>
			<id>1</id>
			<timings>
				<timing name="barrier">0.000677024</timing>
				<timing name="criticalPushBack">2.6537e-05</timing>
				<timing name="criticalRequestValueUpdate">0.622616</timing>
				<timing name="currentGather">0.016081</timing>
				<timing name="currentScatter">1.24514</timing>
			</timings>
			<processedNodes>1111167</processedNodes>
			</thread>
			<thread>
			<id>2</id>
			<timings>
				<timing name="barrier">0.00060773</timing>
				<timing name="criticalPushBack">2.3437e-05</timing>
				<timing name="criticalRequestValueUpdate">0.627115</timing>
				<timing name="currentGather">0.0370945</timing>
				<timing name="currentScatter">0.957961</timing>
			</timings>
			<processedNodes>1111178</processedNodes>
			</thread>
			<thread>
			<id>3</id>
			<timings>
				<timing name="barrier">0.000656593</timing>
				<timing name="criticalPushBack">2.4163e-05</timing>
				<timing name="criticalRequestValueUpdate">0.534628</timing>
				<timing name="currentGather">0.107127</timing>
				<timing name="currentScatter">0.890807</timing>
			</timings>
			<processedNodes>1111172</processedNodes>
			</thread>
			<thread>
			<id>4</id>
			<timings>
				<timing name="barrier">0.000652787</timing>
				<timing name="criticalPushBack">0.0040557</timing>
				<timing name="criticalRequestValueUpdate">0.5662</timing>
				<timing name="currentGather">0.0291478</timing>
				<timing name="currentScatter">1.16174</timing>
			</timings>
			<processedNodes>1111133</processedNodes>
			</thread>
			<thread>
			<id>5</id>
			<timings>
				<timing name="barrier">0.000456304</timing>
				<timing name="criticalPushBack">2.1879e-05</timing>
				<timing name="criticalRequestValueUpdate">0.560362</timing>
				<timing name="currentGather">0.000344402</timing>
				<timing name="currentScatter">1.30049</timing>
			</timings>
			<processedNodes>1111122</processedNodes>
			</thread>
			<thread>
			<id>6</id>
			<timings>
				<timing name="barrier">0.000746694</timing>
				<timing name="criticalPushBack">2.0869e-05</timing>
				<timing name="criticalRequestValueUpdate">0.580718</timing>
				<timing name="currentGather">3.2208e-05</timing>
				<timing name="currentScatter">1.30096</timing>
			</timings>
			<processedNodes>1111154</processedNodes>
			</thread>
			<thread>
			<id>7</id>
			<timings>
				<timing name="barrier">0.00054959</timing>
				<timing name="criticalPushBack">2.3367e-05</timing>
				<timing name="criticalRequestValueUpdate">0.566868</timing>
				<timing name="currentGather">0.0652437</timing>
				<timing name="currentScatter">1.00488</timing>
			</timings>
			<processedNodes>1111138</processedNodes>
			</thread>
			<thread>
			<id>8</id>
			<timings>
				<timing name="barrier">0.000657419</timing>
				<timing name="criticalPushBack">2.245e-05</timing>
				<timing name="criticalRequestValueUpdate">0.545017</timing>
				<timing name="currentGather">0.0172664</timing>
				<timing name="currentScatter">0.98279</timing>
			</timings>
			<processedNodes>1111177</processedNodes>
			</thread>
		</threads>
		<graph>
			<type>SOFTWARE</type>
			<numberOfNodes>10000000</numberOfNodes>
			<numberOfEdges>26974371</numberOfEdges>
			<depth>47</depth>
		</graph>
		<optimistic>true</optimistic>
		<enableAnalysis>true</enableAnalysis>
	</measurement>
</measurements>
