<?xml version="1.0" encoding="UTF-8"?>
<measurements>
	<measurement>
		<date>1449915120</date>
		<errorCode>0</errorCode>
		<numberOfThreads>14</numberOfThreads>
		<processors>24</processors>
		<hostname>e1347</hostname>
		<totalTime>1.03138</totalTime>
		<algorithm>bitset</algorithm>
		<threads>
			<thread>
			<id>0</id>
			<timings>
				<timing name="barrier">1.359e-06</timing>
				<timing name="criticalPushBack">0.0515115</timing>
				<timing name="criticalRequestValueUpdate">0.0332203</timing>
				<timing name="currentGather">0</timing>
				<timing name="currentScatter">0</timing>
			</timings>
			<processedNodes>55711</processedNodes>
			</thread>
			<thread>
			<id>1</id>
			<timings>
				<timing name="barrier">2.522e-06</timing>
				<timing name="criticalPushBack">0.0508816</timing>
				<timing name="criticalRequestValueUpdate">0.0326718</timing>
				<timing name="currentGather">0</timing>
				<timing name="currentScatter">0</timing>
			</timings>
			<processedNodes>54814</processedNodes>
			</thread>
			<thread>
			<id>2</id>
			<timings>
				<timing name="barrier">1.674e-06</timing>
				<timing name="criticalPushBack">0.0516396</timing>
				<timing name="criticalRequestValueUpdate">0.0332338</timing>
				<timing name="currentGather">0</timing>
				<timing name="currentScatter">0</timing>
			</timings>
			<processedNodes>55796</processedNodes>
			</thread>
			<thread>
			<id>3</id>
			<timings>
				<timing name="barrier">1.085e-06</timing>
				<timing name="criticalPushBack">0.0521389</timing>
				<timing name="criticalRequestValueUpdate">0.0344249</timing>
				<timing name="currentGather">0</timing>
				<timing name="currentScatter">0</timing>
			</timings>
			<processedNodes>56317</processedNodes>
			</thread>
			<thread>
			<id>4</id>
			<timings>
				<timing name="barrier">2.49e-06</timing>
				<timing name="criticalPushBack">0.0567728</timing>
				<timing name="criticalRequestValueUpdate">0.034838</timing>
				<timing name="currentGather">0</timing>
				<timing name="currentScatter">0</timing>
			</timings>
			<processedNodes>60775</processedNodes>
			</thread>
			<thread>
			<id>5</id>
			<timings>
				<timing name="barrier">1.437e-06</timing>
				<timing name="criticalPushBack">0.0578006</timing>
				<timing name="criticalRequestValueUpdate">0.035356</timing>
				<timing name="currentGather">0</timing>
				<timing name="currentScatter">0</timing>
			</timings>
			<processedNodes>61658</processedNodes>
			</thread>
			<thread>
			<id>6</id>
			<timings>
				<timing name="barrier">1.409e-06</timing>
				<timing name="criticalPushBack">0.062008</timing>
				<timing name="criticalRequestValueUpdate">0.0403377</timing>
				<timing name="currentGather">0</timing>
				<timing name="currentScatter">0</timing>
			</timings>
			<processedNodes>66323</processedNodes>
			</thread>
			<thread>
			<id>7</id>
			<timings>
				<timing name="barrier">2.326e-06</timing>
				<timing name="criticalPushBack">0.0617405</timing>
				<timing name="criticalRequestValueUpdate">0.0394</timing>
				<timing name="currentGather">0</timing>
				<timing name="currentScatter">0</timing>
			</timings>
			<processedNodes>65645</processedNodes>
			</thread>
			<thread>
			<id>8</id>
			<timings>
				<timing name="barrier">1.709e-06</timing>
				<timing name="criticalPushBack">0.0545471</timing>
				<timing name="criticalRequestValueUpdate">0.0361118</timing>
				<timing name="currentGather">0</timing>
				<timing name="currentScatter">0</timing>
			</timings>
			<processedNodes>58497</processedNodes>
			</thread>
			<thread>
			<id>9</id>
			<timings>
				<timing name="barrier">1.766e-06</timing>
				<timing name="criticalPushBack">0.0530237</timing>
				<timing name="criticalRequestValueUpdate">0.0343073</timing>
				<timing name="currentGather">0</timing>
				<timing name="currentScatter">0</timing>
			</timings>
			<processedNodes>56978</processedNodes>
			</thread>
			<thread>
			<id>10</id>
			<timings>
				<timing name="barrier">2.444e-06</timing>
				<timing name="criticalPushBack">0.0525385</timing>
				<timing name="criticalRequestValueUpdate">0.0339031</timing>
				<timing name="currentGather">0</timing>
				<timing name="currentScatter">0</timing>
			</timings>
			<processedNodes>56279</processedNodes>
			</thread>
			<thread>
			<id>11</id>
			<timings>
				<timing name="barrier">1.476e-06</timing>
				<timing name="criticalPushBack">0.0535504</timing>
				<timing name="criticalRequestValueUpdate">0.0343179</timing>
				<timing name="currentGather">0</timing>
				<timing name="currentScatter">0</timing>
			</timings>
			<processedNodes>57266</processedNodes>
			</thread>
			<thread>
			<id>12</id>
			<timings>
				<timing name="barrier">1.201e-06</timing>
				<timing name="criticalPushBack">0.129513</timing>
				<timing name="criticalRequestValueUpdate">0.244967</timing>
				<timing name="currentGather">0</timing>
				<timing name="currentScatter">0</timing>
			</timings>
			<processedNodes>148190</processedNodes>
			</thread>
			<thread>
			<id>13</id>
			<timings>
				<timing name="barrier">1.12e-06</timing>
				<timing name="criticalPushBack">0.12816</timing>
				<timing name="criticalRequestValueUpdate">0.242062</timing>
				<timing name="currentGather">0</timing>
				<timing name="currentScatter">0</timing>
			</timings>
			<processedNodes>145751</processedNodes>
			</thread>
		</threads>
		<graph>
			<type>RANDOMLIN</type>
			<numberOfNodes>1000000</numberOfNodes>
			<numberOfEdges>2699997</numberOfEdges>
			<depth>22</depth>
			<numberOfChildren>
				<q0>0</q0>
				<q25>0</q25>
				<q50>2</q50>
				<q75>4</q75>
				<q100>17</q100>
			</numberOfChildren>
			<frontSizes>
				<q0>2</q0>
				<q10>39</q10>
				<q20>397</q20>
				<q30>2842</q30>
				<q40>11922</q40>
				<q50>31297</q50>
				<q60>54138</q60>
				<q70>72865</q70>
				<q80>88469</q80>
				<q90>109609</q90>
				<q100>184375</q100>
			</frontSizes>
		</graph>
		<optimistic>true</optimistic>
		<enableAnalysis>true</enableAnalysis>
	</measurement>
</measurements>
