<?xml version="1.0" encoding="UTF-8"?>
<measurements>
	<measurement>
		<date>1449915178</date>
		<errorCode>0</errorCode>
		<numberOfThreads>18</numberOfThreads>
		<processors>24</processors>
		<hostname>e1347</hostname>
		<totalTime>0.739842</totalTime>
		<algorithm>locallist</algorithm>
		<threads>
			<thread>
			<id>0</id>
			<timings>
				<timing name="barrier">0.000669955</timing>
				<timing name="criticalPushBack">0.00134673</timing>
				<timing name="criticalRequestValueUpdate">0.0224592</timing>
				<timing name="currentGather">0.00217606</timing>
				<timing name="currentScatter">0.112519</timing>
			</timings>
			<processedNodes>55592</processedNodes>
			</thread>
			<thread>
			<id>1</id>
			<timings>
				<timing name="barrier">0.000497692</timing>
				<timing name="criticalPushBack">0.000958576</timing>
				<timing name="criticalRequestValueUpdate">0.0203688</timing>
				<timing name="currentGather">0.00324551</timing>
				<timing name="currentScatter">0.120046</timing>
			</timings>
			<processedNodes>55597</processedNodes>
			</thread>
			<thread>
			<id>2</id>
			<timings>
				<timing name="barrier">0.000475573</timing>
				<timing name="criticalPushBack">0.000849832</timing>
				<timing name="criticalRequestValueUpdate">0.019436</timing>
				<timing name="currentGather">0.0014259</timing>
				<timing name="currentScatter">0.12878</timing>
			</timings>
			<processedNodes>55570</processedNodes>
			</thread>
			<thread>
			<id>3</id>
			<timings>
				<timing name="barrier">0.000522232</timing>
				<timing name="criticalPushBack">0.000263704</timing>
				<timing name="criticalRequestValueUpdate">0.0220995</timing>
				<timing name="currentGather">0.0016065</timing>
				<timing name="currentScatter">0.120065</timing>
			</timings>
			<processedNodes>55588</processedNodes>
			</thread>
			<thread>
			<id>4</id>
			<timings>
				<timing name="barrier">0.000455051</timing>
				<timing name="criticalPushBack">0.000990323</timing>
				<timing name="criticalRequestValueUpdate">0.0202626</timing>
				<timing name="currentGather">0.000715237</timing>
				<timing name="currentScatter">0.141879</timing>
			</timings>
			<processedNodes>55574</processedNodes>
			</thread>
			<thread>
			<id>5</id>
			<timings>
				<timing name="barrier">0.000368261</timing>
				<timing name="criticalPushBack">0.000150552</timing>
				<timing name="criticalRequestValueUpdate">0.0165553</timing>
				<timing name="currentGather">0.000619474</timing>
				<timing name="currentScatter">0.133389</timing>
			</timings>
			<processedNodes>55552</processedNodes>
			</thread>
			<thread>
			<id>6</id>
			<timings>
				<timing name="barrier">0.000510294</timing>
				<timing name="criticalPushBack">0.00027169</timing>
				<timing name="criticalRequestValueUpdate">0.0184778</timing>
				<timing name="currentGather">0.0012566</timing>
				<timing name="currentScatter">0.122726</timing>
			</timings>
			<processedNodes>55595</processedNodes>
			</thread>
			<thread>
			<id>7</id>
			<timings>
				<timing name="barrier">0.000432569</timing>
				<timing name="criticalPushBack">0.000459589</timing>
				<timing name="criticalRequestValueUpdate">0.0195111</timing>
				<timing name="currentGather">0.000813887</timing>
				<timing name="currentScatter">0.137905</timing>
			</timings>
			<processedNodes>55597</processedNodes>
			</thread>
			<thread>
			<id>8</id>
			<timings>
				<timing name="barrier">0.000509888</timing>
				<timing name="criticalPushBack">0.000901732</timing>
				<timing name="criticalRequestValueUpdate">0.016278</timing>
				<timing name="currentGather">0.00224978</timing>
				<timing name="currentScatter">0.135277</timing>
			</timings>
			<processedNodes>55596</processedNodes>
			</thread>
			<thread>
			<id>9</id>
			<timings>
				<timing name="barrier">0.000600435</timing>
				<timing name="criticalPushBack">0.00157057</timing>
				<timing name="criticalRequestValueUpdate">0.0188445</timing>
				<timing name="currentGather">0.000484301</timing>
				<timing name="currentScatter">0.12454</timing>
			</timings>
			<processedNodes>55607</processedNodes>
			</thread>
			<thread>
			<id>10</id>
			<timings>
				<timing name="barrier">0.000656287</timing>
				<timing name="criticalPushBack">0.00141556</timing>
				<timing name="criticalRequestValueUpdate">0.0197316</timing>
				<timing name="currentGather">0.00070454</timing>
				<timing name="currentScatter">0.108409</timing>
			</timings>
			<processedNodes>55606</processedNodes>
			</thread>
			<thread>
			<id>11</id>
			<timings>
				<timing name="barrier">0.000564584</timing>
				<timing name="criticalPushBack">0.000525911</timing>
				<timing name="criticalRequestValueUpdate">0.0168378</timing>
				<timing name="currentGather">0.00108602</timing>
				<timing name="currentScatter">0.135189</timing>
			</timings>
			<processedNodes>55555</processedNodes>
			</thread>
			<thread>
			<id>12</id>
			<timings>
				<timing name="barrier">0.000747239</timing>
				<timing name="criticalPushBack">0.000827916</timing>
				<timing name="criticalRequestValueUpdate">0.0649007</timing>
				<timing name="currentGather">0.00133634</timing>
				<timing name="currentScatter">0.113075</timing>
			</timings>
			<processedNodes>55610</processedNodes>
			</thread>
			<thread>
			<id>13</id>
			<timings>
				<timing name="barrier">0.000690718</timing>
				<timing name="criticalPushBack">0.00388281</timing>
				<timing name="criticalRequestValueUpdate">0.0533551</timing>
				<timing name="currentGather">0.00327871</timing>
				<timing name="currentScatter">0.110007</timing>
			</timings>
			<processedNodes>55608</processedNodes>
			</thread>
			<thread>
			<id>14</id>
			<timings>
				<timing name="barrier">0.000516324</timing>
				<timing name="criticalPushBack">0.000403224</timing>
				<timing name="criticalRequestValueUpdate">0.0680182</timing>
				<timing name="currentGather">0.00155402</timing>
				<timing name="currentScatter">0.107777</timing>
			</timings>
			<processedNodes>55609</processedNodes>
			</thread>
			<thread>
			<id>15</id>
			<timings>
				<timing name="barrier">0.000639804</timing>
				<timing name="criticalPushBack">0.00140011</timing>
				<timing name="criticalRequestValueUpdate">0.0589461</timing>
				<timing name="currentGather">0.00233546</timing>
				<timing name="currentScatter">0.103278</timing>
			</timings>
			<processedNodes>55609</processedNodes>
			</thread>
			<thread>
			<id>16</id>
			<timings>
				<timing name="barrier">0.000744432</timing>
				<timing name="criticalPushBack">0.000713057</timing>
				<timing name="criticalRequestValueUpdate">0.0771831</timing>
				<timing name="currentGather">0.000590929</timing>
				<timing name="currentScatter">0.11447</timing>
			</timings>
			<processedNodes>55607</processedNodes>
			</thread>
			<thread>
			<id>17</id>
			<timings>
				<timing name="barrier">0.000721215</timing>
				<timing name="criticalPushBack">0.00154038</timing>
				<timing name="criticalRequestValueUpdate">0.0665508</timing>
				<timing name="currentGather">0.00106821</timing>
				<timing name="currentScatter">0.107554</timing>
			</timings>
			<processedNodes>55609</processedNodes>
			</thread>
		</threads>
		<graph>
			<type>SOFTWARE</type>
			<numberOfNodes>1000000</numberOfNodes>
			<numberOfEdges>2694223</numberOfEdges>
			<depth>40</depth>
			<numberOfChildren>
				<q0>0</q0>
				<q25>0</q25>
				<q50>2</q50>
				<q75>4</q75>
				<q100>37</q100>
			</numberOfChildren>
			<frontSizes>
				<q0>6</q0>
				<q10>89</q10>
				<q20>577</q20>
				<q30>855</q30>
				<q40>1051</q40>
				<q50>2961</q50>
				<q60>6270</q60>
				<q70>14092</q70>
				<q80>33052</q80>
				<q90>91618</q90>
				<q100>269508</q100>
			</frontSizes>
		</graph>
		<optimistic>true</optimistic>
		<enableAnalysis>true</enableAnalysis>
	</measurement>
</measurements>
