<?xml version="1.0" encoding="UTF-8"?>
<measurements>
	<measurement>
		<date>1450019194</date>
		<errorCode>0</errorCode>
		<numberOfThreads>8</numberOfThreads>
		<processors>12</processors>
		<hostname>e1247</hostname>
		<totalTime>3.25795</totalTime>
		<algorithm>bitset</algorithm>
		<graph>
			<type>RANDOMLIN</type>
			<numberOfNodes>800000</numberOfNodes>
			<numberOfEdges>23999115</numberOfEdges>
			<depth>165</depth>
		</graph>
		<optimistic>true</optimistic>
		<enableAnalysis>false</enableAnalysis>
	</measurement>
</measurements>
