<?xml version="1.0" encoding="UTF-8"?>
<measurements>
	<measurement>
		<date>1449951361</date>
		<errorCode>0</errorCode>
		<numberOfThreads>11</numberOfThreads>
		<processors>12</processors>
		<hostname>e1341</hostname>
		<totalTime>0.699687</totalTime>
		<algorithm>bitset</algorithm>
		<threads>
			<thread>
			<id>0</id>
			<timings>
				<timing name="barrier">6.78e-07</timing>
				<timing name="criticalPushBack">0.0506908</timing>
				<timing name="criticalRequestValueUpdate">0.0530895</timing>
				<timing name="currentGather">0</timing>
				<timing name="currentScatter">0</timing>
			</timings>
			<processedNodes>93010</processedNodes>
			</thread>
			<thread>
			<id>1</id>
			<timings>
				<timing name="barrier">6.66e-07</timing>
				<timing name="criticalPushBack">0.0511968</timing>
				<timing name="criticalRequestValueUpdate">0.0530612</timing>
				<timing name="currentGather">0</timing>
				<timing name="currentScatter">0</timing>
			</timings>
			<processedNodes>93508</processedNodes>
			</thread>
			<thread>
			<id>2</id>
			<timings>
				<timing name="barrier">8.86e-07</timing>
				<timing name="criticalPushBack">0.0488887</timing>
				<timing name="criticalRequestValueUpdate">0.0519634</timing>
				<timing name="currentGather">0</timing>
				<timing name="currentScatter">0</timing>
			</timings>
			<processedNodes>88997</processedNodes>
			</thread>
			<thread>
			<id>3</id>
			<timings>
				<timing name="barrier">7.72e-07</timing>
				<timing name="criticalPushBack">0.0500789</timing>
				<timing name="criticalRequestValueUpdate">0.0530413</timing>
				<timing name="currentGather">0</timing>
				<timing name="currentScatter">0</timing>
			</timings>
			<processedNodes>91667</processedNodes>
			</thread>
			<thread>
			<id>4</id>
			<timings>
				<timing name="barrier">8.53e-07</timing>
				<timing name="criticalPushBack">0.0467946</timing>
				<timing name="criticalRequestValueUpdate">0.0495833</timing>
				<timing name="currentGather">0</timing>
				<timing name="currentScatter">0</timing>
			</timings>
			<processedNodes>85984</processedNodes>
			</thread>
			<thread>
			<id>5</id>
			<timings>
				<timing name="barrier">1.001e-06</timing>
				<timing name="criticalPushBack">0.0474726</timing>
				<timing name="criticalRequestValueUpdate">0.0495848</timing>
				<timing name="currentGather">0</timing>
				<timing name="currentScatter">0</timing>
			</timings>
			<processedNodes>85905</processedNodes>
			</thread>
			<thread>
			<id>6</id>
			<timings>
				<timing name="barrier">9.13e-07</timing>
				<timing name="criticalPushBack">0.0474946</timing>
				<timing name="criticalRequestValueUpdate">0.0497721</timing>
				<timing name="currentGather">0</timing>
				<timing name="currentScatter">0</timing>
			</timings>
			<processedNodes>86193</processedNodes>
			</thread>
			<thread>
			<id>7</id>
			<timings>
				<timing name="barrier">1.068e-06</timing>
				<timing name="criticalPushBack">0.0481829</timing>
				<timing name="criticalRequestValueUpdate">0.0498547</timing>
				<timing name="currentGather">0</timing>
				<timing name="currentScatter">0</timing>
			</timings>
			<processedNodes>88142</processedNodes>
			</thread>
			<thread>
			<id>8</id>
			<timings>
				<timing name="barrier">1.087e-06</timing>
				<timing name="criticalPushBack">0.0509181</timing>
				<timing name="criticalRequestValueUpdate">0.0493202</timing>
				<timing name="currentGather">0</timing>
				<timing name="currentScatter">0</timing>
			</timings>
			<processedNodes>94456</processedNodes>
			</thread>
			<thread>
			<id>9</id>
			<timings>
				<timing name="barrier">7.97e-07</timing>
				<timing name="criticalPushBack">0.0522273</timing>
				<timing name="criticalRequestValueUpdate">0.0493544</timing>
				<timing name="currentGather">0</timing>
				<timing name="currentScatter">0</timing>
			</timings>
			<processedNodes>96324</processedNodes>
			</thread>
			<thread>
			<id>10</id>
			<timings>
				<timing name="barrier">1.337e-06</timing>
				<timing name="criticalPushBack">0.0512394</timing>
				<timing name="criticalRequestValueUpdate">0.0473969</timing>
				<timing name="currentGather">0</timing>
				<timing name="currentScatter">0</timing>
			</timings>
			<processedNodes>95814</processedNodes>
			</thread>
		</threads>
		<graph>
			<type>SOFTWARE</type>
			<numberOfNodes>1000000</numberOfNodes>
			<numberOfEdges>2694223</numberOfEdges>
			<depth>41</depth>
		</graph>
		<optimistic>true</optimistic>
		<enableAnalysis>true</enableAnalysis>
	</measurement>
</measurements>
