<?xml version="1.0" encoding="UTF-8"?>
<measurements>
	<measurement>
		<date>1449951372</date>
		<errorCode>0</errorCode>
		<numberOfThreads>10</numberOfThreads>
		<processors>12</processors>
		<hostname>e1011</hostname>
		<totalTime>0.98908</totalTime>
		<algorithm>bitset</algorithm>
		<threads>
			<thread>
			<id>0</id>
			<timings>
				<timing name="barrier">1.696e-06</timing>
				<timing name="criticalPushBack">0.114838</timing>
				<timing name="criticalRequestValueUpdate">0.167129</timing>
				<timing name="currentGather">0</timing>
				<timing name="currentScatter">0</timing>
			</timings>
			<processedNodes>132672</processedNodes>
			</thread>
			<thread>
			<id>1</id>
			<timings>
				<timing name="barrier">1.464e-06</timing>
				<timing name="criticalPushBack">0.123764</timing>
				<timing name="criticalRequestValueUpdate">0.176962</timing>
				<timing name="currentGather">0</timing>
				<timing name="currentScatter">0</timing>
			</timings>
			<processedNodes>143832</processedNodes>
			</thread>
			<thread>
			<id>2</id>
			<timings>
				<timing name="barrier">1.639e-06</timing>
				<timing name="criticalPushBack">0.0743716</timing>
				<timing name="criticalRequestValueUpdate">0.0625317</timing>
				<timing name="currentGather">0</timing>
				<timing name="currentScatter">0</timing>
			</timings>
			<processedNodes>88970</processedNodes>
			</thread>
			<thread>
			<id>3</id>
			<timings>
				<timing name="barrier">1.811e-06</timing>
				<timing name="criticalPushBack">0.0745772</timing>
				<timing name="criticalRequestValueUpdate">0.0627809</timing>
				<timing name="currentGather">0</timing>
				<timing name="currentScatter">0</timing>
			</timings>
			<processedNodes>88729</processedNodes>
			</thread>
			<thread>
			<id>4</id>
			<timings>
				<timing name="barrier">1.36e-06</timing>
				<timing name="criticalPushBack">0.072102</timing>
				<timing name="criticalRequestValueUpdate">0.0591712</timing>
				<timing name="currentGather">0</timing>
				<timing name="currentScatter">0</timing>
			</timings>
			<processedNodes>85706</processedNodes>
			</thread>
			<thread>
			<id>5</id>
			<timings>
				<timing name="barrier">2.319e-06</timing>
				<timing name="criticalPushBack">0.080135</timing>
				<timing name="criticalRequestValueUpdate">0.0703205</timing>
				<timing name="currentGather">0</timing>
				<timing name="currentScatter">0</timing>
			</timings>
			<processedNodes>93873</processedNodes>
			</thread>
			<thread>
			<id>6</id>
			<timings>
				<timing name="barrier">1.4e-06</timing>
				<timing name="criticalPushBack">0.080738</timing>
				<timing name="criticalRequestValueUpdate">0.0716735</timing>
				<timing name="currentGather">0</timing>
				<timing name="currentScatter">0</timing>
			</timings>
			<processedNodes>94721</processedNodes>
			</thread>
			<thread>
			<id>7</id>
			<timings>
				<timing name="barrier">1.315e-06</timing>
				<timing name="criticalPushBack">0.0785727</timing>
				<timing name="criticalRequestValueUpdate">0.0684263</timing>
				<timing name="currentGather">0</timing>
				<timing name="currentScatter">0</timing>
			</timings>
			<processedNodes>91798</processedNodes>
			</thread>
			<thread>
			<id>8</id>
			<timings>
				<timing name="barrier">1.534e-06</timing>
				<timing name="criticalPushBack">0.0761873</timing>
				<timing name="criticalRequestValueUpdate">0.0655348</timing>
				<timing name="currentGather">0</timing>
				<timing name="currentScatter">0</timing>
			</timings>
			<processedNodes>90169</processedNodes>
			</thread>
			<thread>
			<id>9</id>
			<timings>
				<timing name="barrier">1.57e-06</timing>
				<timing name="criticalPushBack">0.0757518</timing>
				<timing name="criticalRequestValueUpdate">0.0651294</timing>
				<timing name="currentGather">0</timing>
				<timing name="currentScatter">0</timing>
			</timings>
			<processedNodes>89530</processedNodes>
			</thread>
		</threads>
		<graph>
			<type>RANDOMLIN</type>
			<numberOfNodes>1000000</numberOfNodes>
			<numberOfEdges>2699997</numberOfEdges>
			<depth>22</depth>
		</graph>
		<optimistic>true</optimistic>
		<enableAnalysis>true</enableAnalysis>
	</measurement>
</measurements>
